demo/__init__.py
demo/admin.py
demo/urls.py
demo/view.py
demo/wsgi.py
demo/management/__init__.py
demo/management/commands/__init__.py
demo/management/commands/bootstrap_river_admin_demo.py
demo/settings/__init__.py
demo/settings/base.py
demo/settings/local.py
demo/settings/prod.py
examples/__init__.py
examples/issue_tracker_example/__init__.py
examples/issue_tracker_example/admin.py
examples/issue_tracker_example/models.py
examples/issue_tracker_example/management/__init__.py
examples/issue_tracker_example/management/commands/__init__.py
examples/issue_tracker_example/management/commands/bootstrap_issue_tracker_example.py
examples/issue_tracker_example/migrations/0001_initial.py
examples/issue_tracker_example/migrations/__init__.py
examples/shipping_example/__init__.py
examples/shipping_example/admin.py
examples/shipping_example/models.py
examples/shipping_example/management/__init__.py
examples/shipping_example/management/commands/__init__.py
examples/shipping_example/management/commands/bootstrap_shipping_example.py
examples/shipping_example/migrations/0001_initial.py
examples/shipping_example/migrations/__init__.py
river_admin/__init__.py
river_admin/site.py
river_admin/urls.py
river_admin/static/favicon.ico
river_admin/static/css/app.d7a88b58.css
river_admin/static/css/chunk-vendors.f492b4c3.css
river_admin/static/fonts/materialdesignicons-webfont.2d0a0d8f.eot
river_admin/static/fonts/materialdesignicons-webfont.b4917be2.woff
river_admin/static/fonts/materialdesignicons-webfont.d0066537.woff2
river_admin/static/fonts/materialdesignicons-webfont.f5111234.ttf
river_admin/static/img/logo.70a5d670.svg
river_admin/static/js/app.7fa0d485.js
river_admin/static/js/chunk-vendors.09114dd8.js
river_admin/templates/index.html
river_admin/views/__init__.py
river_admin/views/approval_hook_view.py
river_admin/views/auth_view.py
river_admin/views/error_code.py
river_admin/views/function_view.py
river_admin/views/serializers.py
river_admin/views/state_view.py
river_admin-0.7.0.dist-info/LICENSE
river_admin-0.7.0.dist-info/METADATA
river_admin-0.7.0.dist-info/WHEEL
river_admin-0.7.0.dist-info/top_level.txt
river_admin-0.7.0.dist-info/RECORD
