Metadata-Version: 1.0
Name: river-admin
Version: 0.7.0
Summary: Administration For django-river
Home-page: https://github.com/javrasya/river-admin.git
Author: Ahmet DAL
Author-email: ceahmetdal@gmail.com
License: BSD
Platform: any
